my_llm_sdk/__init__.py
my_llm_sdk/cli.py
my_llm_sdk/client.py
my_llm_sdk/schemas.py
my_llm_sdk/budget/__init__.py
my_llm_sdk/budget/alerts.py
my_llm_sdk/budget/controller.py
my_llm_sdk/budget/ledger.py
my_llm_sdk/budget/pricing.py
my_llm_sdk/budget/rate_limiter.py
my_llm_sdk/budget/reporter.py
my_llm_sdk/config/__init__.py
my_llm_sdk/config/exceptions.py
my_llm_sdk/config/loader.py
my_llm_sdk/config/models.py
my_llm_sdk/doctor/__init__.py
my_llm_sdk/doctor/checker.py
my_llm_sdk/doctor/report.py
my_llm_sdk/providers/__init__.py
my_llm_sdk/providers/base.py
my_llm_sdk/providers/gemini.py
my_llm_sdk/providers/qwen.py
my_llm_sdk/providers/volcengine.py
my_llm_sdk/services/__init__.py
my_llm_sdk/services/voice.py
my_llm_sdk/utils/__init__.py
my_llm_sdk/utils/media.py
my_llm_sdk/utils/network.py
my_llm_sdk/utils/resilience.py
my_llm_sdk-0.9.3.dist-info/METADATA
my_llm_sdk-0.9.3.dist-info/WHEEL
my_llm_sdk-0.9.3.dist-info/entry_points.txt
my_llm_sdk-0.9.3.dist-info/licenses/LICENSE
my_llm_sdk-0.9.3.dist-info/RECORD
