Metadata-Version: 2.4
Name: my-llm-sdk
Version: 0.9.3
Summary: Vibe Edition LLM SDK
Author-email: Admin <admin@example.com>
License-File: LICENSE
Requires-Python: >=3.10
Requires-Dist: dashscope>=1.14.0
Requires-Dist: google-genai>=1.0.0
Requires-Dist: httpx>=0.24.0
Requires-Dist: pydantic>=2.0.0
Requires-Dist: python-dotenv>=1.0.0
Requires-Dist: pyyaml>=6.0
Requires-Dist: volcengine-python-sdk[ark]>=1.0.0
Provides-Extra: dev
Requires-Dist: pytest; extra == 'dev'
Requires-Dist: pytest-cov; extra == 'dev'
